octodns_scaleway/__init__.py
octodns_scaleway-0.0.4.dist-info/METADATA
octodns_scaleway-0.0.4.dist-info/WHEEL
octodns_scaleway-0.0.4.dist-info/top_level.txt
octodns_scaleway-0.0.4.dist-info/RECORD
