Metadata-Version: 2.1
Name: octodns-scaleway
Version: 0.0.4
Summary: Scaleway DNS provider for octoDNS
Home-page: https://github.com/scaleway/octodns-scaleway
Author: Jeremy JACQUEMIN
Author-email: domain-team@scaleway.com
License: MIT
Platform: UNKNOWN
Requires-Python: >=3.6
Requires-Dist: octodns >=0.9.14
Requires-Dist: requests >=2.27.0
